[
    {
      "id": "0",
      "category": "Celulares",
      "name": "Galaxy A05 Light Green 64GB",
      "descripcion": [
        "Procesador Octa-Core 2GHz, 1.8GHz",
        "Camara frontal 8 MP",
        "Camara trasera 50 MP + 2 MP"
      ],
      "precio": "299.999",
      "descuento": "189.999",
      "imagen": "/productos/Galaxy_a05.png",
      "stock": 5,
      "ranking": 4
    },
    {
      "id": "1",
      "category": "Celulares",
      "name": "Galaxy A24 Black",
      "descripcion": [
        "Procesador Octa-Core 2.2GHz,2GHz",
        "Camara frontal 13.0 MP",
        "Camara trasera 50.0 MP + 5.0 MP"
      ],
      "precio": "579.999",
      "descuento": "399.999",
      "imagen": "/productos/Galaxy_a24Black.png",
      "stock": 3,
      "ranking": 4
    },
    {
      "id": "2",
      "category": "Celulares",
      "name": "Galaxy Z Fold5 Icy Blue 256GB",
      "descripcion": [
        "Procesador Octa-Core 3.36GHz,2.8GHz",
        "Camara frontal 10.0 MP",
        "Camara trasera 50.0 MP + 12.0 MP"
      ],
      "precio": "3.699,999",
      "descuento": "2589.999",
      "imagen": "/productos/Galaxy_zFold.png",
      "stock": 10,
      "ranking": 5
    },
    {
      "id": "3",
      "category": "Tablets",
      "name": "Galaxy Tab S6 Lite + Book Cover",
      "descripcion": [
        "Procesador Octa-Core",
        "Tamaño de pantalla 2000 x 1200",
        "Cámara Frontal 5.0 MP"
      ],
      "precio": "849.999",
      "descuento": "500.999",
      "imagen": "/productos/GalaxyTabS6.png",
      "stock": 7,
      "ranking": 5
    },
    {
      "id": "4",
      "category": "Buds",
      "name": "Galaxy Buds FE Graphite",
      "descripcion": [
        "Número de Micrófonos 6",
        "Altavoces Custom 1-way",
        "Sonido ambiente - SI"
      ],
      "precio": "228.999",
      "descuento": "159.999",
      "imagen": "/productos/GalaxyBudsFE_Graphite.png",
      "stock": 20,
      "ranking": 4
    },
    {
      "id": "5",
      "category": "Buds",
      "name": "Galaxy Buds2 Negro",
      "descripcion": [
        "Número de Micrófonos 6",
        "Versión de Bluetooh - Bluetooth v5.2",
        "Cancelación activa de ruido - SI"
      ],
      "precio": "228.999",
      "descuento": "159.999",
      "imagen": "/productos/GalaxyBuds2Negro.png",
      "stock": 14,
      "ranking": 4
    }
  ]